AshutoshGupta_101703118_Outlier_removal/__init__.py
AshutoshGupta_101703118_Outlier_removal/outlier_removal.py
AshutoshGupta_101703118_Outlier_removal-0.1.3.dist-info/METADATA
AshutoshGupta_101703118_Outlier_removal-0.1.3.dist-info/WHEEL
AshutoshGupta_101703118_Outlier_removal-0.1.3.dist-info/top_level.txt
AshutoshGupta_101703118_Outlier_removal-0.1.3.dist-info/RECORD
