Metadata-Version: 2.1
Name: AshutoshGupta-101703118-Outlier-removal
Version: 0.1.3
Summary: A small example package for removal of outliers in the given dataset
Home-page: UNKNOWN
Author: Ashutosh Gupta
Author-email: agupta12_be17@thapar.edu
License: UNKNOWN
Keywords: command-line,Outliers,outlier-removal,row-removal
Platform: UNKNOWN
Classifier: Programming Language :: Python :: 3
Classifier: License :: OSI Approved :: MIT License
Classifier: Operating System :: OS Independent
Requires-Python: >=3.6
